grok/__init__.py
grok/grok.py
grok/patterns/aws
grok/patterns/bacula
grok/patterns/bind
grok/patterns/bro
grok/patterns/exim
grok/patterns/firewalls
grok/patterns/grok-patterns
grok/patterns/haproxy
grok/patterns/httpd
grok/patterns/java
grok/patterns/junos
grok/patterns/linux-syslog
grok/patterns/maven
grok/patterns/mcollective-patterns
grok/patterns/mongodb
grok/patterns/nagios
grok/patterns/postgresql
grok/patterns/rails
grok/patterns/redis
grok/patterns/ruby
grok/patterns/squid
python_grok-0.3.0.dist-info/LICENSE
python_grok-0.3.0.dist-info/METADATA
python_grok-0.3.0.dist-info/WHEEL
python_grok-0.3.0.dist-info/top_level.txt
python_grok-0.3.0.dist-info/RECORD
