Metadata-Version: 2.1
Name: python-grok
Version: 0.3.0
Summary: A Python package to use Grok expressions
Home-page: https://github.com/dperdices/python-grok
Author: Daniel Perdices
Author-email: daniel.perdices@uam.es
License: MIT
Platform: UNKNOWN
Classifier: License :: OSI Approved :: MIT License
Classifier: Programming Language :: Python :: 3
Classifier: Programming Language :: Python :: 3.6
Classifier: Programming Language :: Python :: 3.7
Requires-Dist: regex
Requires-Dist: importlib-resources
